nskinetics/__init__.py
nskinetics/species.py
nskinetics/doe/__init__.py
nskinetics/doe/fim.py
nskinetics/gui/__init__.py
nskinetics/gui/reaction_network_drawer.py
nskinetics/gui/reaction_system_gui.py
nskinetics/reaction_systems/__init__.py
nskinetics/reaction_systems/nonsteady.py
nskinetics/reaction_systems/predefined.py
nskinetics/reaction_systems/reaction_system.py
nskinetics/reaction_systems/steady.py
nskinetics/reactions/__init__.py
nskinetics/reactions/reaction.py
nskinetics/reactions/utils.py
nskinetics/species/__init__.py
nskinetics/species/enzyme.py
nskinetics/species/species.py
nskinetics/tests/__init__.py
nskinetics/tests/gui_trial.py
nskinetics/tests/test_inverse_modeling_and_doe.py
nskinetics/tests/test_predefined_nonsteady.py
nskinetics/tests/test_reaction_system_solve.py
nskinetics/tests/test_reaction_system_solve_non_log_transform.py
nskinetics/tests/test_sbml_import.py
nskinetics/utils/__init__.py
nskinetics/utils/_argument_checks.py
nskinetics/utils/_create_function.py
nskinetics/utils/_fit.py
nskinetics-0.2.4.dist-info/LICENSE
nskinetics-0.2.4.dist-info/METADATA
nskinetics-0.2.4.dist-info/WHEEL
nskinetics-0.2.4.dist-info/top_level.txt
nskinetics-0.2.4.dist-info/RECORD
