Metadata-Version: 2.1
Name: nskinetics
Version: 0.2.4
Summary: Simulation of Non-Steady state enzyme Kinetics and inhibitory phenomena
Home-page: https://github.com/sarangbhagwat/nskinetics
Download-URL: https://github.com/sarangbhagwat/nskinetics.git
Author: Sarang S. Bhagwat
Author-email: sarangbhagwat.developer@gmail.com
License: MIT
Keywords: reaction kinetics,biocatalysis,biomanufacturing,bioprocess engineering,mass and energy balance,process simulation,biorefinery,biofuel,bioproducts
Platform: Windows
Platform: Mac
Platform: Linux
Classifier: License :: OSI Approved :: MIT License
Classifier: Development Status :: 3 - Alpha
Classifier: Environment :: Console
Classifier: Topic :: Scientific/Engineering
Classifier: Topic :: Scientific/Engineering :: Chemistry
Classifier: Topic :: Scientific/Engineering :: Mathematics
Classifier: Topic :: Scientific/Engineering :: Bio-Informatics
Classifier: Intended Audience :: Developers
Classifier: Intended Audience :: Education
Classifier: Intended Audience :: Manufacturing
Classifier: Intended Audience :: Science/Research
Classifier: Natural Language :: English
Classifier: Operating System :: MacOS
Classifier: Operating System :: Microsoft :: Windows
Classifier: Operating System :: POSIX
Classifier: Operating System :: POSIX :: BSD
Classifier: Operating System :: POSIX :: Linux
Classifier: Operating System :: Unix
Classifier: Programming Language :: Python :: 3.9
Classifier: Programming Language :: Python :: 3.10
Classifier: Programming Language :: Python :: Implementation :: CPython
Classifier: Topic :: Education
Requires-Python: >=3.9
License-File: LICENSE
Requires-Dist: IPython>=7.9.0
Requires-Dist: numpy<2.0.0,>=1.26.4
Requires-Dist: numba<1.0.0,>=0.60.0
Requires-Dist: scipy<2.0.0,>=1.13.1
Requires-Dist: matplotlib<4.0.0,>=3.5.2
Requires-Dist: xlsxwriter<4.0.0,>=3.2.5
Requires-Dist: scikit-learn
Requires-Dist: pandas<3.0.0,>=2.2.2
